gflabel/__init__.py
gflabel/bases/__init__.py
gflabel/bases/cullenect.py
gflabel/bases/modern.py
gflabel/bases/none.py
gflabel/bases/plain.py
gflabel/bases/pred.py
gflabel/cli.py
gflabel/fragments.py
gflabel/label.py
gflabel/options.py
gflabel/resources/LICENSE_OpenSans
gflabel/resources/LICENSE_symbols
gflabel/resources/OpenSans-Bold.ttf
gflabel/resources/OpenSans-Italic.ttf
gflabel/resources/OpenSans-Regular.ttf
gflabel/resources/chris-pikul-symbols.zip
gflabel/util.py
gflabel-0.2.0.dist-info/LICENSE.txt
gflabel-0.2.0.dist-info/METADATA
gflabel-0.2.0.dist-info/WHEEL
gflabel-0.2.0.dist-info/entry_points.txt
gflabel-0.2.0.dist-info/RECORD
