Metadata-Version: 2.1
Name: gflabel
Version: 0.2.0
Summary: 
License: BSD-3-Clause
Author: Nicholas Devenish
Author-email: ndevenish@gmail.com
Requires-Python: >=3.10,<3.13
Classifier: License :: OSI Approved :: BSD License
Classifier: Programming Language :: Python :: 3
Classifier: Programming Language :: Python :: 3.10
Classifier: Programming Language :: Python :: 3.11
Classifier: Programming Language :: Python :: 3.12
Requires-Dist: build123d (>=0.8.0)
Requires-Dist: pint (>=0.24.4,<0.25.0)
Requires-Dist: rich (>=13.7.1,<14.0.0)
